gtirb_pprinter-2.2.2.dist-info/METADATA
gtirb_pprinter-2.2.2.dist-info/entry_points.txt
gtirb_pprinter-2.2.2.dist-info/top_level.txt
gtirb_pprinter-2.2.2.dist-info/WHEEL
gtirb_pprinter-2.2.2.dist-info/RECORD
gtirb_pprinter/py.typed
gtirb_pprinter/__init__.py
gtirb_pprinter/gtirb-pprinter
gtirb_pprinter/__main__.py
gtirb_pprinter/version.py
gtirb_pprinter/.libs/libgtirb_pprinter.so.2
gtirb_pprinter/.libs/libgtirb_layout.so.2.2.2
gtirb_pprinter/.libs/libcapstone.so.5
gtirb_pprinter/.libs/libgtirb.so.2.3.0
gtirb_pprinter/.libs/libgtirb_layout.so.2
gtirb_pprinter/.libs/libgtirb_pprinter.so.2.2.2
