Metadata-Version: 2.1
Name: gtirb-pprinter
Version: 2.2.2
Summary: Pretty printer from GTIRB to assembly code
Home-page: https://github.com/grammatech/gtirb-pprinter
Author: GrammaTech, Inc.
Author-email: gtirb@grammatech.com
License: MIT
Keywords: reverse-engineering,disassembler,binary-analysis,intermediate-representation,binary-rewriting,gtirb
Classifier: License :: OSI Approved :: MIT License
Classifier: Topic :: Software Development
Classifier: Development Status :: 5 - Production/Stable
Classifier: Intended Audience :: Developers
Classifier: Intended Audience :: System Administrators
Classifier: Operating System :: POSIX
Requires-Python: >=3.6
Requires-Dist: gtirb (==2.3.0)
Requires-Dist: importlib-resources ; python_version < "3.9"
